[
  {
    "id": 1,
    "name": "主城·奥尔登里奇",
    "nameEn": "City of Aldenreach",
    "key": "MainTown",
    "area": "阿瑟隆王国",
    "level": "不限",
    "difficulty": "安全",
    "boss": "无",
    "drops": ["生命药水", "法力药水", "随机装备盒", "随从缰绳"],
    "description": "一座由小城堡守护的带城墙集市城镇，也是阿瑟隆王国最后的安全避风港。英雄们在此休整、交易、补给，然后出征对抗地狱之主的黑暗。",
    "enemies": []
  },
  {
    "id": 2,
    "name": "国王森林",
    "nameEn": "Kings Woods",
    "key": "Forest",
    "area": "阿瑟隆王国",
    "level": "1-15级",
    "difficulty": "简单",
    "boss": "森林巨魔",
    "drops": ["生命药水", "狼之缰绳", "野猪缰绳", "黑蜘蛛缰绳"],
    "description": "冒险者离开主城后到达的第一片森林。黑蜘蛛、毒液蜘蛛与树桩怪在这里出没，是新手练级和获取早期野兽随从的主要区域。",
    "enemies": ["黑蜘蛛", "毒液蜘蛛", "树桩怪", "灰森林狼", "野猪"]
  },
  {
    "id": 3,
    "name": "北山地穴",
    "nameEn": "Northhill Crypt",
    "key": "Dungeon",
    "area": "阿瑟隆王国",
    "level": "15-30级",
    "difficulty": "普通",
    "boss": "骷髅队长",
    "drops": ["哥布林战士缰绳", "骷髅弓箭手缰绳", "骷髅战士缰绳", "铁剑"],
    "description": "位于艾尔文平原下方的古老墓穴。哥布林战士、骷髅弓箭手与骷髅战士盘踞于此，是中期装备与随从材料的重要来源。",
    "enemies": ["哥布林战士", "骷髅弓箭手", "骷髅战士"]
  },
  {
    "id": 4,
    "name": "北山地穴下层",
    "nameEn": "Northhill Crypt Lower",
    "key": "DungeonL",
    "area": "阿瑟隆王国",
    "level": "25-40级",
    "difficulty": "困难",
    "boss": "兽人酋长",
    "drops": ["兽人战士缰绳", "食人魔缰绳", "诅咒精华碎片", "骷髅钥匙"],
    "description": "北山地穴的更深层，这里盘踞着兽人战士、食人魔与黑暗精灵法师。击败守关Boss可获得进入更高级区域的钥匙材料。",
    "enemies": ["兽人战士", "食人魔", "黑暗精灵法师"]
  },
  {
    "id": 5,
    "name": "国王森林南部",
    "nameEn": "Kings Woods South",
    "key": "CorruptForest",
    "area": "阿瑟隆王国",
    "level": "35-50级",
    "difficulty": "困难",
    "boss": "远古橡树树人",
    "drops": ["树桩怪缰绳", "远古橡树树人缰绳", "血月狼人缰绳", "传说防具"],
    "description": "被腐化侵蚀的国王森林南部，树桩怪、血月狼人与远古橡树树人在这里游荡。高稀有度自然随从与传说装备的主要产出地。",
    "enemies": ["树桩怪", "血月狼人", "远古橡树树人"]
  },
  {
    "id": 6,
    "name": "神话裂隙",
    "nameEn": "Mythic Rift",
    "key": "MythicDungeon",
    "area": "阿瑟隆王国",
    "level": "50+级",
    "difficulty": "噩梦",
    "boss": "幼年黑龙",
    "drops": ["龙之缰绳", "传说武器", "神圣装备"],
    "description": "勇者的终极试炼之地。裂隙深处潜藏着幼年黑龙等神话级敌人，是获取最顶级装备与稀有随从缰绳的必经之路。",
    "enemies": ["幼年黑龙"]
  },
  {
    "id": 7,
    "name": "封锁区域",
    "nameEn": "Locked Area",
    "key": "LockedMap",
    "area": "阿瑟隆王国",
    "level": "??",
    "difficulty": "未知",
    "boss": "未知",
    "drops": ["???"],
    "description": "当前尚未开放的区域，等待后续版本解锁。",
    "enemies": []
  }
]
